<?xml version="1.0" encoding="UTF-8" standalone="yes"?>
<userSammlung>
    <userliste>
        <benutzername>Peter</benutzername>
        <benutzersprache>de</benutzersprache>
        <passwort>eli</passwort>
    </userliste>
    <userliste>
        <benutzername>Klaus</benutzername>
        <benutzersprache>de</benutzersprache>
        <passwort>eli</passwort>
    </userliste>
    <userliste>
        <benutzername>dani</benutzername>
        <benutzersprache>EN</benutzersprache>
        <passwort>eli</passwort>
    </userliste>
    <userliste>
        <benutzername>brunnert</benutzername>
        <benutzersprache>EN</benutzersprache>
        <passwort>eli</passwort>
    </userliste>
    <userliste>
        <benutzername>manfred</benutzername>
        <benutzersprache>Deutsch</benutzersprache>
        <passwort>eli</passwort>
    </userliste>
    <userliste>
        <benutzername>Marius</benutzername>
        <benutzersprache>DE</benutzersprache>
        <passwort>eli</passwort>
    </userliste>
    <userliste>
        <benutzername>Pit</benutzername>
        <benutzersprache>english</benutzersprache>
        <passwort>a</passwort>
    </userliste>
    <userliste>
        <benutzername>T</benutzername>
        <benutzersprache>français</benutzersprache>
        <passwort>t</passwort>
    </userliste>
    <userliste>
        <benutzername>palmer</benutzername>
        <benutzersprache>Deutsch</benutzersprache>
        <passwort>eli</passwort>
    </userliste>
    <userliste>
        <benutzername>dani</benutzername>
        <benutzersprache>Deutsch</benutzersprache>
        <passwort>eli</passwort>
    </userliste>
    <userliste>
        <benutzername>neu</benutzername>
        <benutzersprache>français</benutzersprache>
        <passwort>eli</passwort>
    </userliste>
    <userliste>
        <benutzername>sprache</benutzername>
        <benutzersprache>DE</benutzersprache>
        <passwort>eli</passwort>
    </userliste>
    <userliste>
        <benutzername>sprache2</benutzername>
        <benutzersprache>FR</benutzersprache>
        <passwort>eli</passwort>
    </userliste>
    <userliste>
        <benutzername>Demouser</benutzername>
        <benutzersprache>DE</benutzersprache>
        <passwort>eli</passwort>
    </userliste>
    <userliste>
        <benutzername>Test123</benutzername>
        <benutzersprache>DE</benutzersprache>
        <passwort>123</passwort>
    </userliste>
</userSammlung>
